{
    "key": "group_6827a8136abaf",
    "title": "Theme Settings",
    "fields": [
        {
            "key": "field_6827a81369d50",
            "label": "General",
            "name": "",
            "aria-label": "",
            "type": "tab",
            "instructions": "",
            "required": 0,
            "conditional_logic": 0,
            "wrapper": {
                "width": "",
                "class": "",
                "id": ""
            },
            "placement": "top",
            "endpoint": 0,
            "selected": 0
        },
        {
            "key": "field_6827a82369d51",
            "label": "Social Media",
            "name": "social_media",
            "aria-label": "",
            "type": "group",
            "instructions": "",
            "required": 0,
            "conditional_logic": 0,
            "wrapper": {
                "width": "",
                "class": "",
                "id": ""
            },
            "layout": "row",
            "sub_fields": [
                {
                    "key": "field_6827a83469d52",
                    "label": "Facebook",
                    "name": "facebook",
                    "aria-label": "",
                    "type": "url",
                    "instructions": "",
                    "required": 0,
                    "conditional_logic": 0,
                    "wrapper": {
                        "width": "",
                        "class": "",
                        "id": ""
                    },
                    "default_value": "",
                    "allow_in_bindings": 0,
                    "placeholder": ""
                },
                {
                    "key": "field_6827a83f69d54",
                    "label": "Instagram",
                    "name": "instagram",
                    "aria-label": "",
                    "type": "url",
                    "instructions": "",
                    "required": 0,
                    "conditional_logic": 0,
                    "wrapper": {
                        "width": "",
                        "class": "",
                        "id": ""
                    },
                    "default_value": "",
                    "allow_in_bindings": 0,
                    "placeholder": ""
                }
            ]
        },
        {
            "key": "field_6840877584393",
            "label": "Footer",
            "name": "",
            "aria-label": "",
            "type": "tab",
            "instructions": "",
            "required": 0,
            "conditional_logic": 0,
            "wrapper": {
                "width": "",
                "class": "",
                "id": ""
            },
            "placement": "top",
            "endpoint": 0,
            "selected": 0
        },
        {
            "key": "field_684087d984394",
            "label": "App Screenshot",
            "name": "app_screenshot",
            "aria-label": "",
            "type": "image",
            "instructions": "",
            "required": 0,
            "conditional_logic": 0,
            "wrapper": {
                "width": "",
                "class": "",
                "id": ""
            },
            "return_format": "id",
            "library": "all",
            "min_width": "",
            "min_height": "",
            "min_size": "",
            "max_width": "",
            "max_height": "",
            "max_size": "",
            "mime_types": "",
            "allow_in_bindings": 0,
            "preview_size": "thumbnail"
        },
        {
            "key": "field_684087f284395",
            "label": "Buttons",
            "name": "footer_buttons",
            "aria-label": "",
            "type": "repeater",
            "instructions": "",
            "required": 0,
            "conditional_logic": 0,
            "wrapper": {
                "width": "",
                "class": "",
                "id": ""
            },
            "layout": "row",
            "pagination": 0,
            "min": 0,
            "max": 0,
            "collapsed": "",
            "button_label": "Add a Button",
            "rows_per_page": 20,
            "sub_fields": [
                {
                    "key": "field_6840880b84396",
                    "label": "Button",
                    "name": "button",
                    "aria-label": "",
                    "type": "clone",
                    "instructions": "",
                    "required": 0,
                    "conditional_logic": 0,
                    "wrapper": {
                        "width": "",
                        "class": "",
                        "id": ""
                    },
                    "clone": [
                        "group_67b740db570e7"
                    ],
                    "display": "group",
                    "layout": "row",
                    "prefix_label": 0,
                    "prefix_name": 0,
                    "parent_repeater": "field_684087f284395"
                }
            ]
        },
        {
            "key": "field_6840882284397",
            "label": "Accepted Cards",
            "name": "accepted_cards",
            "aria-label": "",
            "type": "gallery",
            "instructions": "",
            "required": 0,
            "conditional_logic": 0,
            "wrapper": {
                "width": "",
                "class": "",
                "id": ""
            },
            "return_format": "id",
            "library": "all",
            "min": "",
            "max": "",
            "min_width": "",
            "min_height": "",
            "min_size": "",
            "max_width": "",
            "max_height": "",
            "max_size": "",
            "mime_types": "",
            "insert": "append",
            "preview_size": "thumbnail"
        },
        {
            "key": "field_6840883784398",
            "label": "Text under accepted cards",
            "name": "accepted_cards_text",
            "aria-label": "",
            "type": "text",
            "instructions": "",
            "required": 0,
            "conditional_logic": 0,
            "wrapper": {
                "width": "",
                "class": "",
                "id": ""
            },
            "default_value": "",
            "maxlength": "",
            "allow_in_bindings": 0,
            "placeholder": "",
            "prepend": "",
            "append": ""
        },
        {
            "key": "field_6834c4dcc7888",
            "label": "Course Page",
            "name": "",
            "aria-label": "",
            "type": "tab",
            "instructions": "",
            "required": 0,
            "conditional_logic": 0,
            "wrapper": {
                "width": "",
                "class": "",
                "id": ""
            },
            "placement": "top",
            "endpoint": 0,
            "selected": 0
        },
        {
            "key": "field_6834c4eac7889",
            "label": "Blueprints",
            "name": "course_blueprints",
            "aria-label": "",
            "type": "clone",
            "instructions": "",
            "required": 0,
            "conditional_logic": 0,
            "wrapper": {
                "width": "",
                "class": "",
                "id": ""
            },
            "clone": [
                "group_68108d094053f"
            ],
            "display": "group",
            "layout": "row",
            "prefix_label": 0,
            "prefix_name": 0
        }
    ],
    "location": [
        [
            {
                "param": "options_page",
                "operator": "==",
                "value": "theme-settings"
            }
        ]
    ],
    "menu_order": 0,
    "position": "normal",
    "style": "default",
    "label_placement": "top",
    "instruction_placement": "label",
    "hide_on_screen": "",
    "active": true,
    "description": "",
    "show_in_rest": 0,
    "modified": 1749059656
}
